LICENSE.txt
MANIFEST.in
README
README.md
setup.py
examples/buttons_raw.py
examples/buttons_xy.py
examples/hello.py
examples/information.py
examples/launchpad_pressure.py
examples/launchpad_pressure_xy.py
examples/launchpad_pro.py
examples/launchpad_rgb-fire.py
examples/launchpad_rgb-pulse.py
examples/launchpad_rgb.py
examples/midi_events.py
examples/midifighter_led_modes.py
examples/midifighter_text.py
images/lppro_colorcodes.png
images/mf64_colorcodes.png
images/promk3_transmit.png
launchpad_py/__init__.py
launchpad_py/charset.py
launchpad_py/launchpad.py
launchpad_py.egg-info/PKG-INFO
launchpad_py.egg-info/SOURCES.txt
launchpad_py.egg-info/dependency_links.txt
launchpad_py.egg-info/top_level.txt