Metadata-Version: 1.0
Name: launchpad_py
Version: 0.9.1
Summary: A Novation Launchpad control suite for Python
Home-page: https://github.com/FMMT666/launchpad.py
Author: FMMT666(ASkr)
Author-email: fmmt666@users.noreply.github.com
License: CC BY 4.0
Keywords: novation launchpad midi
Platform: UNKNOWN
